twitter_space_downloader/__init__.py
twitter_space_downloader/main.py
twitter_space_downloader-1.4.1.dist-info/licenses/LICENSE
twitter_space_downloader-1.4.1.dist-info/METADATA
twitter_space_downloader-1.4.1.dist-info/WHEEL
twitter_space_downloader-1.4.1.dist-info/entry_points.txt
twitter_space_downloader-1.4.1.dist-info/top_level.txt
twitter_space_downloader-1.4.1.dist-info/RECORD
