Metadata-Version: 2.4
Name: twitter-space-downloader
Version: 1.4.1
Summary: High-performance asynchronous Twitter/X Space downloader with concurrent download and automatic merging
Author-email: Mike <mike@example.com>
License: MIT License
Project-URL: Homepage, https://github.com/learnerlj/twitter-space-downloader
Project-URL: Repository, https://github.com/learnerlj/twitter-space-downloader
Project-URL: Issues, https://github.com/learnerlj/twitter-space-downloader/issues
Keywords: twitter,space,downloader,audio,async
Classifier: Development Status :: 5 - Production/Stable
Classifier: Intended Audience :: End Users/Desktop
Classifier: Operating System :: OS Independent
Classifier: Programming Language :: Python :: 3
Classifier: Programming Language :: Python :: 3.7
Classifier: Programming Language :: Python :: 3.8
Classifier: Programming Language :: Python :: 3.9
Classifier: Programming Language :: Python :: 3.10
Classifier: Programming Language :: Python :: 3.11
Classifier: Programming Language :: Python :: 3.12
Classifier: Topic :: Multimedia :: Sound/Audio
Classifier: Topic :: Internet :: WWW/HTTP
Classifier: Topic :: System :: Archiving
Requires-Python: >=3.10
License-File: LICENSE
Requires-Dist: aiohttp>=3.8.0
Requires-Dist: aiofiles>=22.0.0
Requires-Dist: yt-dlp>=2023.1.6
Requires-Dist: ffmpeg-python>=0.2.0
Requires-Dist: rich>=13.0.0
Requires-Dist: click>=8.0.0
Provides-Extra: dev
Requires-Dist: pytest>=6.0; extra == "dev"
Requires-Dist: black; extra == "dev"
Requires-Dist: flake8; extra == "dev"
Requires-Dist: mypy; extra == "dev"
Dynamic: license-file
